nastar/__init__.py
nastar/cli.py
nastar/encoder.py
nastar-2.0.0.dist-info/licenses/LICENSE
nastar-2.0.0.dist-info/METADATA
nastar-2.0.0.dist-info/WHEEL
nastar-2.0.0.dist-info/entry_points.txt
nastar-2.0.0.dist-info/top_level.txt
nastar-2.0.0.dist-info/RECORD
