Metadata-Version: 2.4
Name: nastar
Version: 2.0.0
Summary: Python code protection with direct execution
Author-email: Anak Kecil <anakkecil@example.com>
License: Nastar Code Protection License
Classifier: Programming Language :: Python :: 3
Classifier: Intended Audience :: Developers
Classifier: Topic :: Software Development :: Libraries
License-File: LICENSE
Dynamic: license-file
